dacp/__init__.py
dacp/_version.py
dacp/solver.py
dacp/benchmark/benchmark.py
dacp/benchmark/mem_2d_eigvals_only.png
dacp/benchmark/mem_2d_eigvals_only_2d.png
dacp/benchmark/time_2d_eigvals_only.png
dacp/benchmark/time_2d_eigvals_only_2d.png
dacp/benchmark/data/data_benchmark_eigvals_only.nc
dacp/benchmark/data/data_benchmark_eigvals_only_2d.nc
dacp/examples/example.py
dacp/tests/__init__.py
dacp/tests/test_eigvalsh.py
pydacp-1.0.1.dist-info/METADATA
pydacp-1.0.1.dist-info/WHEEL
pydacp-1.0.1.dist-info/licenses/AUTHORS.md
pydacp-1.0.1.dist-info/licenses/LICENSE
pydacp-1.0.1.dist-info/RECORD
