Metadata-Version: 2.3
Name: pyDACP
Version: 1.0.1
Summary: Package to compute eigenvalues using the dual applications of Chebyshev polynomials algorithm
Project-URL: Documentation, https://pydacp.readthedocs.io/en/latest/
Project-URL: Repository, https://gitlab.kwant-project.org/qt/pyDACP
Project-URL: Bug Tracker, https://gitlab.kwant-project.org/qt/pyDACP/-/issues
Author: pyDACP developers
License-File: AUTHORS.md
License-File: LICENSE
Classifier: Development Status :: 4 - Beta
Classifier: Intended Audience :: Science/Research
Classifier: License :: OSI Approved :: BSD License
Classifier: Programming Language :: Python :: 3.9
Classifier: Programming Language :: Python :: 3.10
Classifier: Programming Language :: Python :: 3.11
Requires-Python: >=3.9
Requires-Dist: numpy>=1.23
Requires-Dist: packaging>=22.0
Requires-Dist: scipy>=1.8
